{
  "forge_marker": 1,
  "defaults": {
    "model": "gtlitecore:pump_casing",
    "textures": {
      "all": "gtlitecore:blocks/rendering_error"
    }
  },
  "variants": {
    "variant": {
      "lv": {
        "model": "gtlitecore:pump_casing",
        "textures": {
          "all": "gtlitecore:blocks/casings/tiered/lv"
        }
      },
      "mv": {
        "model": "gtlitecore:pump_casing",
        "textures": {
          "all": "gtlitecore:blocks/casings/tiered/mv"
        }
      },
      "hv": {
        "model": "gtlitecore:pump_casing",
        "textures": {
          "all": "gtlitecore:blocks/casings/tiered/hv"
        }
      },
      "ev": {
        "model": "gtlitecore:pump_casing",
        "textures": {
          "all": "gtlitecore:blocks/casings/tiered/ev"
        }
      },
      "iv": {
        "model": "gtlitecore:pump_casing",
        "textures": {
          "all": "gtlitecore:blocks/casings/tiered/iv"
        }
      },
      "luv": {
        "model": "gtlitecore:pump_casing",
        "textures": {
          "all": "gtlitecore:blocks/casings/tiered/luv"
        }
      },
      "zpm": {
        "model": "gtlitecore:pump_casing",
        "textures": {
          "all": "gtlitecore:blocks/casings/tiered/zpm"
        }
      },
      "uv": {
        "model": "gtlitecore:pump_casing",
        "textures": {
          "all": "gtlitecore:blocks/casings/tiered/uv"
        }
      },
      "uhv": {
        "model": "gtlitecore:pump_casing",
        "textures": {
          "all": "gtlitecore:blocks/casings/tiered/uhv"
        }
      },
      "uev": {
        "model": "gtlitecore:pump_casing",
        "textures": {
          "all": "gtlitecore:blocks/casings/tiered/uev"
        }
      },
      "uiv": {
        "model": "gtlitecore:pump_casing",
        "textures": {
          "all": "gtlitecore:blocks/casings/tiered/uiv"
        }
      },
      "uxv": {
        "model": "gtlitecore:pump_casing",
        "textures": {
          "all": "gtlitecore:blocks/casings/tiered/uxv"
        }
      },
      "opv": {
        "model": "gtlitecore:pump_casing",
        "textures": {
          "all": "gtlitecore:blocks/casings/tiered/opv"
        }
      },
      "max": {
        "model": "gtlitecore:pump_casing",
        "textures": {
          "all": "gtlitecore:blocks/casings/tiered/max"
        }
      }
    }
  }
}